nlf.py
nlatest_files-1.0.2.dist-info/DESCRIPTION.rst
nlatest_files-1.0.2.dist-info/METADATA
nlatest_files-1.0.2.dist-info/RECORD
nlatest_files-1.0.2.dist-info/WHEEL
nlatest_files-1.0.2.dist-info/entry_points.txt
nlatest_files-1.0.2.dist-info/metadata.json
nlatest_files-1.0.2.dist-info/top_level.txt
