Metadata-Version: 2.0
Name: nlatest-files
Version: 1.0.2
Summary: Easy symlinks to the n latest files in a directory
Home-page: https://github.com/DomWilliams0/nlatest-files
Author: Dom Williams
Author-email: nlf@domwillia.ms
License: GPLv3
Keywords: files directory versioning latest screenshot
Platform: UNKNOWN
Classifier: Development Status :: 5 - Production/Stable
Classifier: Intended Audience :: Developers
Classifier: Intended Audience :: End Users/Desktop
Classifier: License :: OSI Approved :: GNU General Public License v3 (GPLv3)
Classifier: Programming Language :: Python :: 3
Requires-Dist: ConfigArgParse (==0.12.0)
